odoo/addons/purchase_default_terms_conditions/README.rst
odoo/addons/purchase_default_terms_conditions/__init__.py
odoo/addons/purchase_default_terms_conditions/__manifest__.py
odoo/addons/purchase_default_terms_conditions/i18n/pt_BR.po
odoo/addons/purchase_default_terms_conditions/i18n/purchase_default_terms_conditions.pot
odoo/addons/purchase_default_terms_conditions/models/__init__.py
odoo/addons/purchase_default_terms_conditions/models/res_company.py
odoo/addons/purchase_default_terms_conditions/models/res_config_settings.py
odoo/addons/purchase_default_terms_conditions/readme/CONFIGURE.rst
odoo/addons/purchase_default_terms_conditions/readme/CONTRIBUTORS.rst
odoo/addons/purchase_default_terms_conditions/readme/CREDITS.rst
odoo/addons/purchase_default_terms_conditions/readme/DESCRIPTION.rst
odoo/addons/purchase_default_terms_conditions/readme/USAGE.rst
odoo/addons/purchase_default_terms_conditions/static/description/banner.png
odoo/addons/purchase_default_terms_conditions/static/description/icon.png
odoo/addons/purchase_default_terms_conditions/static/description/index.html
odoo/addons/purchase_default_terms_conditions/views/res_config_settings.xml
odoo12_addon_purchase_default_terms_conditions-12.0.1.0.0.99.dev4.dist-info/METADATA
odoo12_addon_purchase_default_terms_conditions-12.0.1.0.0.99.dev4.dist-info/WHEEL
odoo12_addon_purchase_default_terms_conditions-12.0.1.0.0.99.dev4.dist-info/top_level.txt
odoo12_addon_purchase_default_terms_conditions-12.0.1.0.0.99.dev4.dist-info/RECORD
